egstudio/__init__.py
egstudio/cli.py
egstudio/debug.py
egstudio/event_stream.py
egstudio/job_settings.py
egstudio/app/__init__.py
egstudio/app/api.py
egstudio/app/config.py
egstudio/app/mixin.py
egstudio/app/swagger.py
egstudio/app/blueprints/__init__.py
egstudio/app/blueprints/assets/__init__.py
egstudio/app/blueprints/assets/resources.py
egstudio/app/blueprints/auth/__init__.py
egstudio/app/blueprints/auth/resources.py
egstudio/app/blueprints/breakdown/__init__.py
egstudio/app/blueprints/breakdown/resources.py
egstudio/app/blueprints/comments/__init__.py
egstudio/app/blueprints/comments/resources.py
egstudio/app/blueprints/crud/__init__.py
egstudio/app/blueprints/crud/asset_instance.py
egstudio/app/blueprints/crud/attachment_file.py
egstudio/app/blueprints/crud/base.py
egstudio/app/blueprints/crud/comments.py
egstudio/app/blueprints/crud/custom_action.py
egstudio/app/blueprints/crud/day_off.py
egstudio/app/blueprints/crud/department.py
egstudio/app/blueprints/crud/entity.py
egstudio/app/blueprints/crud/entity_link.py
egstudio/app/blueprints/crud/entity_type.py
egstudio/app/blueprints/crud/event.py
egstudio/app/blueprints/crud/file_status.py
egstudio/app/blueprints/crud/metadata_descriptor.py
egstudio/app/blueprints/crud/milestone.py
egstudio/app/blueprints/crud/news.py
egstudio/app/blueprints/crud/notification.py
egstudio/app/blueprints/crud/organisation.py
egstudio/app/blueprints/crud/output_file.py
egstudio/app/blueprints/crud/output_type.py
egstudio/app/blueprints/crud/person.py
egstudio/app/blueprints/crud/playlist.py
egstudio/app/blueprints/crud/preview_background_file.py
egstudio/app/blueprints/crud/preview_file.py
egstudio/app/blueprints/crud/project.py
egstudio/app/blueprints/crud/project_status.py
egstudio/app/blueprints/crud/schedule_item.py
egstudio/app/blueprints/crud/search_filter.py
egstudio/app/blueprints/crud/search_filter_group.py
egstudio/app/blueprints/crud/software.py
egstudio/app/blueprints/crud/status_automation.py
egstudio-0.1.dist-info/LICENSE
egstudio-0.1.dist-info/METADATA
egstudio-0.1.dist-info/WHEEL
egstudio-0.1.dist-info/top_level.txt
egstudio-0.1.dist-info/RECORD
