Metadata-Version: 2.1
Name: egstudio
Version: 0.1
Summary: A brief description of your package
Home-page: UNKNOWN
Author: vrutansh
Author-email: your.email@example.com
License: UNKNOWN
Platform: UNKNOWN
Classifier: Programming Language :: Python :: 3
Classifier: License :: OSI Approved :: MIT License
Classifier: Operating System :: OS Independent
Requires-Python: >=3.6
License-File: LICENSE
